graphene_jwt_auth/__init__.py
graphene_jwt_auth/authentication.py
graphene_jwt_auth/compat.py
graphene_jwt_auth/exceptions.py
graphene_jwt_auth/forms.py
graphene_jwt_auth/middleware.py
graphene_jwt_auth/mixins.py
graphene_jwt_auth/models.py
graphene_jwt_auth/payload.py
graphene_jwt_auth/settings.py
graphene_jwt_auth/status.py
graphene_jwt_auth/views.py
graphene_jwt_auth/blacklist/__init__.py
graphene_jwt_auth/blacklist/admin.py
graphene_jwt_auth/blacklist/forms.py
graphene_jwt_auth/blacklist/models.py
graphene_jwt_auth/blacklist/utils.py
graphene_jwt_auth/blacklist/migrations/0001_initial.py
graphene_jwt_auth/blacklist/migrations/__init__.py
graphene_jwt_auth/blacklist/migrations/__pycache__/__init__.cpython-35.pyc
graphene_jwt_auth/graphene/__init__.py
graphene_jwt_auth/graphene/mutation.py
graphene_jwt_auth/graphene/permissions.py
graphene_jwt_auth/graphene/queries.py
graphene_jwt_auth/graphene/utils.py
graphene_jwt_auth/graphene/views.py
graphene_jwt_auth/graphene/relay/__init__.py
graphene_jwt_auth/graphene/relay/mutation.py
graphene_jwt_auth/longrunningtoken/__init__.py
graphene_jwt_auth/longrunningtoken/admin.py
graphene_jwt_auth/longrunningtoken/forms.py
graphene_jwt_auth/longrunningtoken/models.py
graphene_jwt_auth/longrunningtoken/utils.py
graphene_jwt_auth/longrunningtoken/migrations/0001_initial.py
graphene_jwt_auth/longrunningtoken/migrations/__init__.py
graphene_jwt_auth/longrunningtoken/migrations/__pycache__/__init__.cpython-35.pyc
graphene_jwt_auth/migrations/__init__.py
graphene_jwt_auth/migrations/__pycache__/__init__.cpython-35.pyc
graphene_jwt_auth/utils/__init__.py
graphene_jwt_auth/utils/core.py
graphene_jwt_auth/utils/serializer_helpers.py
graphene_jwt_auth-0.0.2.dist-info/DESCRIPTION.rst
graphene_jwt_auth-0.0.2.dist-info/METADATA
graphene_jwt_auth-0.0.2.dist-info/RECORD
graphene_jwt_auth-0.0.2.dist-info/WHEEL
graphene_jwt_auth-0.0.2.dist-info/metadata.json
graphene_jwt_auth-0.0.2.dist-info/top_level.txt
