Metadata-Version: 2.0
Name: graphene-jwt-auth
Version: 0.0.2
Summary: JSON Web Token based authentication for Django and Graphene
Home-page: https://github.com/darwin4031/graphene-jwt-auth
Author: Darwin Herlinmanda Cahyadi
Author-email: darwin4031@gmail.com
License: MIT
Download-URL: https://github.com/darwin4031/graphene-jwt-auth/archive/0.0.2.tar.gz
Platform: UNKNOWN
Classifier: Development Status :: 3 - Alpha
Classifier: Environment :: Web Environment
Classifier: Framework :: Django
Classifier: Intended Audience :: Developers
Classifier: License :: OSI Approved :: MIT License
Classifier: Operating System :: OS Independent
Classifier: Programming Language :: Python
Classifier: Programming Language :: Python :: 3
Classifier: Topic :: Internet :: WWW/HTTP
Requires-Dist: PyJWT (>=1.4.0,<2.0.0)
Requires-Dist: django
Requires-Dist: graphene-django
